fountas_pinnell_utils/__init__.py
fountas_pinnell_utils/rosters.py
wf_fountas_pinnell_utils-1.0.0.dist-info/LICENSE
wf_fountas_pinnell_utils-1.0.0.dist-info/METADATA
wf_fountas_pinnell_utils-1.0.0.dist-info/WHEEL
wf_fountas_pinnell_utils-1.0.0.dist-info/top_level.txt
wf_fountas_pinnell_utils-1.0.0.dist-info/RECORD
